{"stat.chestOpened":1,"stat.flyOneCm":51177,"stat.deaths":2,"stat.walkOneCm":101133,"stat.drop":2,"stat.jump":125,"stat.swimOneCm":132,"stat.playOneMinute":9861,"achievement.openInventory":1,"stat.fallOneCm":3711,"stat.useItem.minecraft.egg":1,"stat.leaveGame":1,"stat.damageTaken":655780,"stat.damageDealt":80,"stat.crouchOneCm":177,"stat.killEntity.Zombie":1,"stat.timeSinceDeath":0,"stat.sprintOneCm":61901,"stat.mobKills":1,"achievement.exploreAllBiomes":{"value":0,"progress":["Birch Forest Hills","Birch Forest","River","Plains","Extreme Hills","TaigaHills"]},"stat.craftingTableInteraction":1}